{
  "project_info": {
    "project_number": "695529667344",
    "firebase_url": "https://charitable-413ec-default-rtdb.firebaseio.com",
    "project_id": "charitable-413ec",
    "storage_bucket": "charitable-413ec.appspot.com"
  },
  "client": [
    {
      "client_info": {
        "mobilesdk_app_id": "1:695529667344:android:ef9e501e2d594e7cbbc395",
        "android_client_info": {
          "package_name": "edu.neu.charitable"
        }
      },
      "oauth_client": [
        {
          "client_id": "695529667344-55efs7c9fqevckm7e0gg19cm8lctdvf4.apps.googleusercontent.com",
          "client_type": 1,
          "android_info": {
            "package_name": "edu.neu.charitable",
            "certificate_hash": "877ddf456f8638bba32d46e09f832b324d201a7d"
          }
        },
        {
          "client_id": "695529667344-6bj3vcbk12nh3hjflgedtd35e1d9n7vo.apps.googleusercontent.com",
          "client_type": 3
        }
      ],
      "api_key": [
        {
          "current_key": "AIzaSyB5XRo6XRN9S-HnlFZxwf1vITArVCTjm2A"
        }
      ],
      "services": {
        "appinvite_service": {
          "other_platform_oauth_client": [
            {
              "client_id": "695529667344-6bj3vcbk12nh3hjflgedtd35e1d9n7vo.apps.googleusercontent.com",
              "client_type": 3
            }
          ]
        }
      }
    }
  ],
  "configuration_version": "1"
}